MyMeSDK/__init__.py
MyMeSDK/api.py
MyMeSDK/cloud_request.py
MyMeSDK/constants.py
MyMeSDK/database_manager.py
MyMeSDK/delegates.py
MyMeSDK/myme_device.py
MyMeSDK/myme_objects.py
MyMeSDK/myme_visual_topic.py
MyMeSDK/packet_parser.py
MyMeSDK/user_callback_req_types.py
MyMeSDK/algo/__init__.py
MyMeSDK/algo/face_session.py
MyMeSDK/algo/face_session_manager.py
MyMeSDK/bluetooth/__init__.py
MyMeSDK/bluetooth/bluetooth_manager.py
MyMeSDK/bluetooth/packet_assembler.py
MyMeSDK/myme_requests/__init__.py
MyMeSDK/myme_requests/request_types.py
MyMeSDK/pygatt/__init__.py
MyMeSDK/pygatt/device.py
MyMeSDK/pygatt/exceptions.py
MyMeSDK/pygatt/util.py
MyMeSDK/pygatt/backends/__init__.py
MyMeSDK/pygatt/backends/backend.py
MyMeSDK/pygatt/backends/bgapi/__init__.py
MyMeSDK/pygatt/backends/bgapi/bgapi.py
MyMeSDK/pygatt/backends/bgapi/bglib.py
MyMeSDK/pygatt/backends/bgapi/constants.py
MyMeSDK/pygatt/backends/bgapi/device.py
MyMeSDK/pygatt/backends/bgapi/error_codes.py
MyMeSDK/pygatt/backends/bgapi/exceptions.py
MyMeSDK/pygatt/backends/bgapi/packets.py
MyMeSDK/pygatt/backends/bgapi/util.py
MyMeSDK/pygatt/backends/gatttool/__init__.py
MyMeSDK/pygatt/backends/gatttool/device.py
MyMeSDK/pygatt/backends/gatttool/gatttool.py
MyMeSDK/utils/__init__.py
MyMeSDK/utils/appdirs.py
MyMeSDK/utils/sdk_utils.py
MyMeSDK-1.0.9.dist-info/DESCRIPTION.rst
MyMeSDK-1.0.9.dist-info/METADATA
MyMeSDK-1.0.9.dist-info/RECORD
MyMeSDK-1.0.9.dist-info/WHEEL
MyMeSDK-1.0.9.dist-info/entry_points.txt
MyMeSDK-1.0.9.dist-info/metadata.json
MyMeSDK-1.0.9.dist-info/top_level.txt
