Metadata-Version: 2.0
Name: MyMeSDK
Version: 1.0.9
Summary: MyMe Python SDK
Home-page: http://myme.orcam.com
Author: OrCam ltd.
Author-email: amit.man@orcam.com
License: MIT
Keywords: wearables
Platform: UNKNOWN
Classifier: Development Status :: 3 - Alpha
Classifier: Intended Audience :: Developers
Classifier: Topic :: Software Development :: Build Tools
Classifier: License :: OSI Approved :: MIT License
Classifier: Programming Language :: Python :: 2
Classifier: Programming Language :: Python :: 2.6
Classifier: Programming Language :: Python :: 2.7
Requires-Dist: Pillow
Requires-Dist: enum34
Requires-Dist: ndg-httpsclient
Requires-Dist: numpy (>=1.9.0)
Requires-Dist: pyserial
Requires-Dist: requests
Requires-Dist: sqlalchemy
Requires-Dist: urllib3
